{
  "project_info": {
    "project_number": "158860716859",
    "firebase_url": "https://international-b4efd.firebaseio.com",
    "project_id": "international-b4efd",
    "storage_bucket": "international-b4efd.appspot.com"
  },
  "client": [
    {
      "client_info": {
        "mobilesdk_app_id": "1:158860716859:android:251502056d5b969221651e",
        "android_client_info": {
          "package_name": "com.international.digitAT"
        }
      },
      "oauth_client": [
        {
          "client_id": "158860716859-v8affr7opoi0lts8uk6pn74m4ts4v3ig.apps.googleusercontent.com",
          "client_type": 1,
          "android_info": {
            "package_name": "com.international.digitAT",
            "certificate_hash": "4e04c9b2ed9e237335b6d4f28813cb0cc257b538"
          }
        },
        {
          "client_id": "158860716859-pq4hlk2rtf0odatsp5vb358761alqgpg.apps.googleusercontent.com",
          "client_type": 3
        }
      ],
      "api_key": [
        {
          "current_key": "AIzaSyBxAIjm8bLxOB0HyV0n_K-MK2p-g280PGk"
        }
      ],
      "services": {
        "appinvite_service": {
          "other_platform_oauth_client": [
            {
              "client_id": "158860716859-pq4hlk2rtf0odatsp5vb358761alqgpg.apps.googleusercontent.com",
              "client_type": 3
            }
          ]
        }
      }
    }
  ],
  "configuration_version": "1"
}